idgrms/__init__.py
idgrms/data.py
idgrms/plotdgrms.py
idgrms-0.1.1.data/scripts/interactive_diagrams.py
idgrms-0.1.1.dist-info/METADATA
idgrms-0.1.1.dist-info/RECORD
idgrms-0.1.1.dist-info/WHEEL
idgrms-0.1.1.dist-info/top_level.txt
