Metadata-Version: 2.1
Name: idgrms
Version: 0.1.1
Summary: Display points on different diagrams and interact with them
Home-page: https://github.com/pbrus/interactive-diagrams
Author: Przemysław Bruś
License: UNKNOWN
Keywords: interactive,diagrams,scatter,plot
Platform: UNKNOWN
Classifier: Development Status :: 5 - Production/Stable
Classifier: Intended Audience :: Science/Research
Classifier: License :: OSI Approved :: MIT License
Classifier: Operating System :: OS Independent
Classifier: Programming Language :: Python
Classifier: Programming Language :: Python :: 3.5
Classifier: Programming Language :: Python :: 3.6
Classifier: Programming Language :: Python :: 3.7
Classifier: Topic :: Scientific/Engineering :: Astronomy
Classifier: Topic :: Utilities
Requires-Dist: numpy (>=1.14.0)
Requires-Dist: matplotlib
